{
  "name": "fontello",
  "css_prefix_text": "icon-",
  "css_use_suffix": false,
  "hinting": true,
  "units_per_em": 1000,
  "ascent": 850,
  "glyphs": [
    {
      "uid": "212ab54aac31030950fec3e2448ebee9",
      "css": "budget",
      "code": 59392,
      "src": "modernpics"
    },
    {
      "uid": "90e0aff5c929e444038355746a952aaf",
      "css": "food-stock",
      "code": 62097,
      "src": "fontawesome"
    },
    {
      "uid": "d7059fc5329e1a7fcab80ba87831c957",
      "css": "food-diary",
      "code": 59393,
      "src": "iconic"
    },
    {
      "uid": "w3nzesrlbezu6f30q7ytyq919p6gdlb6",
      "css": "home",
      "code": 59394,
      "src": "typicons"
    },
    {
      "uid": "8b80d36d4ef43889db10bc1f0dc9a862",
      "css": "user",
      "code": 59395,
      "src": "fontawesome"
    },
    {
      "uid": "c55fdf978f617992b43ee7cbaa6ef87e",
      "css": "menu",
      "code": 61448,
      "src": "mfglabs"
    },
    {
      "uid": "3ba4275937db277075fc47d6b5a69a2e",
      "css": "back",
      "code": 59396,
      "src": "entypo"
    },
    {
      "uid": "5308d824454af8ec7835786e272361a9",
      "css": "level-up",
      "code": 59398,
      "src": "entypo"
    },
    {
      "uid": "ce5e29aa5208417700e7f7012a236c00",
      "css": "undo",
      "code": 59399,
      "src": "iconic"
    },
    {
      "uid": "21b42d3c3e6be44c3cc3d73042faa216",
      "css": "filter",
      "code": 61918,
      "src": "fontawesome"
    },
    {
      "uid": "e99461abfef3923546da8d745372c995",
      "css": "cog",
      "code": 59400,
      "src": "fontawesome"
    },
    {
      "uid": "f6d72aa5ef8e8f0e553012af9a29a87e",
      "css": "left",
      "code": 61815,
      "src": "fontawesome"
    },
    {
      "uid": "fb94e23ae1e7660aa63cc5f351ec7560",
      "css": "right",
      "code": 61816,
      "src": "fontawesome"
    },
    {
      "uid": "f06941dfcb90dc24b987d810898c4310",
      "css": "down",
      "code": 61813,
      "src": "fontawesome"
    },
    {
      "uid": "720f98e7580b7987c8dc542513d1d440",
      "css": "up",
      "code": 61814,
      "src": "fontawesome"
    },
    {
      "uid": "895405dfac8a3b7b2f23b183c6608ee6",
      "css": "export",
      "code": 59401,
      "src": "fontawesome"
    },
    {
      "uid": "8663320a860b00f26e94d3d15c9ba99a",
      "css": "clock",
      "code": 59402,
      "src": "entypo"
    },
    {
      "uid": "1e394b6cd5e0da3e10d8e4f3fe355960",
      "css": "adult",
      "code": 59403,
      "src": "elusive"
    },
    {
      "uid": "f04a5d24e9e659145b966739c4fde82a",
      "css": "bookmark",
      "code": 59404,
      "src": "fontawesome"
    },
    {
      "uid": "2f5ef6f6b7aaebc56458ab4e865beff5",
      "css": "bookmark-empty",
      "code": 61591,
      "src": "fontawesome"
    },
    {
      "uid": "44e04715aecbca7f266a17d5a7863c68",
      "css": "plus",
      "code": 59405,
      "src": "fontawesome"
    },
    {
      "uid": "d73eceadda1f594cec0536087539afbf",
      "css": "heart",
      "code": 59406,
      "src": "fontawesome"
    },
    {
      "uid": "f3dc2d6d8fe9cf9ebff84dc260888cdf",
      "css": "heart-empty",
      "code": 59407,
      "src": "fontawesome"
    },
    {
      "uid": "d84a06c5ce6da9ebdc9b0a5cb94db4c4",
      "css": "heartbeat",
      "code": 61982,
      "src": "fontawesome"
    },
    {
      "uid": "ff1cd67dfb30d12965d950e8a609c31f",
      "css": "chart-pie",
      "code": 59409,
      "src": "iconic"
    },
    {
      "uid": "554ee96588a6c9ee632624cd051fe6fc",
      "css": "pie-chart",
      "code": 61952,
      "src": "fontawesome"
    },
    {
      "uid": "f618b862657f76a7649d4f9a8d6a965a",
      "css": "checklist-2",
      "code": 59408,
      "src": "custom_icons",
      "selected": true,
      "svg": {
        "path": "M978.5 17.8H239C227.2 17.8 217.5 27.4 217.5 39.3V466.4H21.5C9.6 466.4 0 476 0 487.8V851.9C0 923.7 58.4 982.2 130.2 982.2 132.1 982.2 869.7 982.2 869.7 982.2 941.6 982.2 1000 923.7 1000 851.9V39.3C1000 27.4 990.4 17.8 978.5 17.8ZM43 851.9V509.3H217.5V851.9C217.5 900 178.4 939.2 130.2 939.2 82.1 939.2 43 900 43 851.9ZM957 851.9C957 900 917.9 939.2 869.7 939.2H226.8C247.7 916.1 260.5 885.5 260.5 851.9V60.8H957V851.9ZM578.6 265.9H853.9C865.8 265.9 875.4 256.3 875.4 244.5 875.4 232.6 865.8 223 853.9 223H578.6C566.7 223 557.1 232.6 557.1 244.5 557.1 256.3 566.7 265.9 578.6 265.9ZM578.6 501.9H853.9C865.8 501.9 875.4 492.3 875.4 480.4 875.4 468.6 865.8 459 853.9 459H578.6C566.7 459 557.1 468.6 557.1 480.4 557.1 492.3 566.7 501.9 578.6 501.9ZM578.6 737.9H853.9C865.8 737.9 875.4 728.3 875.4 716.4 875.4 704.6 865.8 694.9 853.9 694.9H578.6C566.7 694.9 557.1 704.6 557.1 716.4 557.1 728.3 566.7 737.9 578.6 737.9ZM380.4 290.1C384.4 294.4 390.1 296.8 396 296.8 396.1 296.8 396.1 296.8 396.2 296.8 402.2 296.8 407.8 294.3 411.9 289.8L529.9 160.6C537.9 151.9 537.2 138.3 528.5 130.3 519.7 122.3 506.1 122.9 498.1 131.7L395.7 243.8 363.9 210C355.7 201.4 342.1 201 333.5 209.2 324.9 217.3 324.5 230.9 332.6 239.5L380.4 290.1ZM498.1 377.9L395.7 490 363.9 456.3C355.7 447.6 342.1 447.3 333.5 455.4 324.9 463.6 324.5 477.1 332.6 485.8L380.4 536.3C384.4 540.6 390.1 543.1 396 543.1 396.1 543.1 396.1 543.1 396.2 543.1 402.2 543 407.8 540.5 411.9 536.1L529.9 406.9C537.9 398.1 537.2 384.5 528.5 376.5S506.1 369.1 498.1 377.9ZM498.1 624.1L395.7 736.3 363.9 702.5C355.7 693.9 342.1 693.5 333.5 701.6 324.9 709.8 324.5 723.4 332.6 732L380.4 782.6C384.4 786.9 390.1 789.3 396 789.3 396.1 789.3 396.1 789.3 396.2 789.3 402.2 789.2 407.8 786.7 411.9 782.3L529.9 653.1C537.9 644.3 537.2 630.7 528.5 622.7 519.7 614.7 506.1 615.4 498.1 624.1Z",
        "width": 1000
      },
      "search": [
        "checklist-2"
      ]
    },
    {
      "uid": "ac84957742fec1c186b6c9cc482a991f",
      "css": "checklist-3",
      "code": 59397,
      "src": "custom_icons",
      "selected": true,
      "svg": {
        "path": "M89.3 0C40 0 0 40 0 89.3V321.4H178.6V89.3C178.6 40 138.6 0 89.3 0ZM428.6 857.1V910.7C428.6 944.3 415 976.5 390.9 1000H910.7C960 999.9 999.9 960 1000 910.7V857.1H428.6ZM392.9 839.3C392.9 829.4 400.9 821.4 410.7 821.4H821.4V89.3C821.4 40 781.4 0.1 732.1 0H176.6C200.7 23.5 214.3 55.7 214.3 89.3V910.7C214.3 960 254.3 999.9 303.6 1000 352.9 999.9 392.8 960 392.9 910.7V839.3ZM517.9 214.3H732.1C742 214.3 750 222.3 750 232.1 750 242 742 250 732.1 250H517.9C508 250 500 242 500 232.1 500 222.3 508 214.3 517.9 214.3ZM517.9 428.6H732.1C742 428.6 750 436.6 750 446.4 750 456.3 742 464.3 732.1 464.3H517.9C508 464.3 500 456.3 500 446.4 500 436.6 508 428.6 517.9 428.6ZM517.9 642.9H732.1C742 642.9 750 650.9 750 660.7 750 670.6 742 678.6 732.1 678.6H517.9C508 678.6 500 670.6 500 660.7 500 650.9 508 642.9 517.9 642.9ZM290.9 237.4C297.9 230.4 309.2 230.4 316.2 237.4L337.4 258.5 432.1 132.1C436 127 442.2 124.4 448.6 125.1 454.9 125.9 460.3 130 462.8 135.8 465.4 141.7 464.5 148.5 460.7 153.6L353.6 296.4C350.5 300.6 345.7 303.2 340.6 303.6H339.3C334.5 303.6 330 301.7 326.7 298.3L290.9 262.6C284 255.7 284 244.3 290.9 237.4ZM290.9 451.7C297.9 444.7 309.2 444.7 316.2 451.7L337.4 472.8 432.1 346.4C436 341.3 442.2 338.7 448.6 339.4 454.9 340.2 460.3 344.3 462.8 350.1 465.4 356 464.5 362.8 460.7 367.9L353.6 510.7C350.5 514.9 345.7 517.5 340.6 517.9H339.3C334.5 517.9 330 516 326.7 512.6L290.9 476.9C284 469.9 284 458.6 290.9 451.7ZM353.6 725C350.5 729.2 345.7 731.8 340.6 732.1H339.3C334.6 732.1 330 730.3 326.7 726.9L290.9 691.2C284 684.2 284 672.9 290.9 665.9 297.9 659 309.2 659 316.2 665.9L337.4 687.1 432.1 560.7C438.1 552.8 449.3 551.2 457.1 557.1 465 563.1 466.6 574.3 460.7 582.1L353.6 725Z",
        "width": 1000
      },
      "search": [
        "checklist-3"
      ]
    },
    {
      "uid": "7f8110ca8a6249a336d95ab625d691bd",
      "css": "checklist-4",
      "code": 59410,
      "src": "custom_icons",
      "selected": true,
      "svg": {
        "path": "M730.1 0H36.3C13.5 0-5 18.5-5 41.3V897.1C-5 919.9 13.5 938.4 36.3 938.4H730.1C752.9 938.4 771.5 919.9 771.5 897.1V41.3C771.5 18.5 752.9 0 730.1 0ZM260.5 746L184.6 850.4C179.5 857.3 171.5 861.5 162.9 861.7 162.7 861.7 162.5 861.7 162.3 861.7 153.9 861.7 146 857.9 140.8 851.4L108.5 811.1C99 799.2 100.9 781.9 112.8 772.4 124.7 762.9 142 764.8 151.5 776.7L153.9 779.7 161.2 788.8 215.9 713.6C224.9 701.3 242.1 698.6 254.4 707.5 266.7 716.5 269.4 733.7 260.5 746ZM260.5 554.9L184.6 659.4C179.5 666.3 171.5 670.5 162.9 670.7 162.7 670.7 162.5 670.7 162.3 670.7 153.9 670.7 146 666.9 140.8 660.4L108.5 620.1C99 608.2 100.9 590.9 112.8 581.4 124.7 571.9 142 573.8 151.5 585.7L153.9 588.7 161.2 597.8 215.9 522.6C224.9 510.3 242.1 507.6 254.4 516.5 266.7 525.4 269.4 542.6 260.5 554.9ZM260.5 363.9L184.6 468.3C179.5 475.3 171.5 479.5 162.9 479.7 162.7 479.7 162.5 479.7 162.3 479.7 153.9 479.7 146 475.9 140.8 469.3L108.5 429C99 417.2 100.9 399.8 112.8 390.3 124.7 380.8 142 382.8 151.5 394.6L153.9 397.7 161.2 406.8 215.9 331.5C224.9 319.3 242.1 316.5 254.4 325.5 266.7 334.4 269.4 351.6 260.5 363.9ZM260.5 172.9L184.6 277.3C179.5 284.2 171.5 288.4 162.9 288.6 162.7 288.6 162.5 288.6 162.3 288.6 153.9 288.6 146 284.8 140.8 278.3L108.5 238C99 226.1 100.9 208.8 112.8 199.3S142 191.7 151.5 203.6L153.9 206.6 161.2 215.8 215.9 140.5C224.9 128.2 242.1 125.5 254.4 134.4S269.4 160.6 260.5 172.9ZM653.4 824.3H355.9C340.7 824.3 328.4 812 328.4 796.8 328.4 781.6 340.7 769.3 355.9 769.3H653.4C668.6 769.3 680.9 781.6 680.9 796.8 680.9 812 668.6 824.3 653.4 824.3ZM653.4 625.4H355.9C340.7 625.4 328.4 613.1 328.4 597.9 328.4 582.7 340.7 570.4 355.9 570.4H653.4C668.6 570.4 680.9 582.7 680.9 597.9 680.9 613.1 668.6 625.4 653.4 625.4ZM653.4 426.5H355.9C340.7 426.5 328.4 414.2 328.4 399S340.7 371.5 355.9 371.5H653.4C668.6 371.5 680.9 383.8 680.9 399S668.6 426.5 653.4 426.5ZM653.4 227.6H355.9C340.7 227.6 328.4 215.3 328.4 200.1 328.4 184.9 340.7 172.6 355.9 172.6H653.4C668.6 172.6 680.9 184.9 680.9 200.1 680.9 215.3 668.6 227.6 653.4 227.6ZM653.4 227.6",
        "width": 1000
      },
      "search": [
        "checklist-4"
      ]
    },
    {
      "uid": "26916c470f04e65541a6bdb9a82a4b02",
      "css": "recipe-book",
      "code": 59411,
      "src": "custom_icons",
      "selected": true,
      "svg": {
        "path": "M871.6 864.8V54.1C871.6 24.3 847.3 0 817.6 0H182.4C152.7 0 128.4 24.3 128.4 54.1V108.1 864.9 945.9C128.4 975.7 152.7 1000 182.4 1000H817.6C837.3 1000 854.7 989.1 864.1 973H236.5C206.7 973 182.4 948.7 182.4 919H817.6C847.3 918.9 871.6 894.6 871.6 864.8ZM313 723.2C303.4 732.9 287.7 732.9 278 723.2 268.4 713.6 268.4 697.9 278.1 688.3L432.2 534.1 467.1 569.1 313 723.2ZM688.1 725.4C678.5 735.1 662.8 735 653.1 725.4L391.1 463.3C389.9 462.2 389.3 460.7 388.4 459.4 350.5 477.5 296.1 464.5 255.7 424.1 207.4 375.8 197.7 307.3 233.8 271.2 270 235 338.5 244.8 386.7 293 427.1 333.5 440.1 387.9 422.1 425.8 423.4 426.7 424.8 427.2 426 428.4L688.1 690.5C697.7 700.1 697.8 715.8 688.1 725.4ZM784.1 348.3L671.8 460.5C670.9 461.4 669.9 461.9 668.9 462.5 630.6 496.6 591.2 496.8 559.2 476.2 558.6 477 558.3 477.9 557.6 478.6L531.8 504.4 496.9 469.5 522.7 443.7C523.4 443 524.3 442.7 525.1 442.1 504.4 410 504.7 370.7 538.8 332.4 539.4 331.4 539.8 330.3 540.7 329.5L653 217.2C658.2 212 666.6 212 671.8 217.2 677 222.4 677 230.8 671.7 235.9L563.2 344.5 581.9 363.2 690.5 254.7C695.6 249.5 704 249.5 709.2 254.7 714.3 259.8 714.3 268.1 709.2 273.4L600.6 381.9 619.4 400.7 727.9 292.1C733.1 287 741.5 286.9 746.6 292.1S751.8 305.7 746.6 310.8L638.1 419.4 656.8 438.1 765.3 329.5C770.5 324.3 779 324.3 784.1 329.5 789.3 334.7 789.3 343.1 784.1 348.3Z",
        "width": 1000
      },
      "search": [
        "recipebook"
      ]
    },
    {
      "uid": "269973f2d5484fecb8ac84b303282bbb",
      "css": "checklist-1",
      "code": 59412,
      "src": "custom_icons",
      "selected": true,
      "svg": {
        "path": "M95.4 720.6H196V821.1H95.4ZM95.4 720.6M95.4 486H196V586.5H95.4ZM95.4 486M715.4 0H78.2C89.3 14.4 95.4 32.1 95.4 50.3V100.5H765.7V50.3C765.7 22.5 743.2 0 715.4 0ZM715.4 0M61.9 100.5V50.3C61.9 22.5 39.4 0 11.6 0 2.4 0-5.1 7.5-5.1 16.8V921.7C-5.1 930.9 2.4 938.4 11.6 938.4H648.4C657.7 938.4 665.2 930.9 665.2 921.7V134.1H95.4C76.9 134.1 61.9 119.1 61.9 100.5ZM229.5 821.1C229.5 839.6 214.5 854.6 196 854.6H95.4C76.9 854.6 61.9 839.6 61.9 821.1V720.6C61.9 702.1 76.9 687.1 95.4 687.1H196C214.5 687.1 229.5 702.1 229.5 720.6ZM229.5 586.5C229.5 605 214.5 620 196 620H95.4C76.9 620 61.9 605 61.9 586.5V486C61.9 467.5 76.9 452.4 95.4 452.4H196C214.5 452.4 229.5 467.5 229.5 486ZM614.9 821.1H531.1C521.9 821.1 514.4 813.6 514.4 804.4 514.4 795.1 521.9 787.6 531.1 787.6H614.9C624.2 787.6 631.7 795.1 631.7 804.4 631.7 813.6 624.2 821.1 614.9 821.1ZM614.9 754.1H447.3C438.1 754.1 430.6 746.6 430.6 737.3 430.6 728.1 438.1 720.6 447.3 720.6H614.9C624.2 720.6 631.7 728.1 631.7 737.3 631.7 746.6 624.2 754.1 614.9 754.1ZM614.9 586.5H531.1C521.9 586.5 514.4 579 514.4 569.8 514.4 560.5 521.9 553 531.1 553H614.9C624.2 553 631.7 560.5 631.7 569.8 631.7 579 624.2 586.5 614.9 586.5ZM614.9 519.5H447.3C438.1 519.5 430.6 512 430.6 502.7 430.6 493.5 438.1 486 447.3 486H614.9C624.2 486 631.7 493.5 631.7 502.7 631.7 512 624.2 519.5 614.9 519.5ZM614.9 351.9H531.1C521.9 351.9 514.4 344.4 514.4 335.1 514.4 325.9 521.9 318.4 531.1 318.4H614.9C624.2 318.4 631.7 325.9 631.7 335.1 631.7 344.4 624.2 351.9 614.9 351.9ZM447.3 251.4H614.9C624.2 251.4 631.7 258.9 631.7 268.1 631.7 277.4 624.2 284.9 614.9 284.9H447.3C438.1 284.9 430.6 277.4 430.6 268.1 430.6 258.9 438.1 251.4 447.3 251.4ZM296.5 251.4H380.3C389.5 251.4 397.1 258.9 397.1 268.1 397.1 277.4 389.5 284.9 380.3 284.9H296.5C287.3 284.9 279.7 277.4 279.7 268.1 279.7 258.9 287.3 251.4 296.5 251.4ZM296.5 318.4H464.1C473.3 318.4 480.8 325.9 480.8 335.1 480.8 344.4 473.3 351.9 464.1 351.9H296.5C287.3 351.9 279.7 344.4 279.7 335.1 279.7 325.9 287.3 318.4 296.5 318.4ZM296.5 486H380.3C389.5 486 397.1 493.5 397.1 502.7 397.1 512 389.5 519.5 380.3 519.5H296.5C287.3 519.5 279.7 512 279.7 502.7 279.7 493.5 287.3 486 296.5 486ZM296.5 553H464.1C473.3 553 480.8 560.5 480.8 569.8 480.8 579 473.3 586.5 464.1 586.5H296.5C287.3 586.5 279.7 579 279.7 569.8 279.7 560.5 287.3 553 296.5 553ZM296.5 720.6H380.3C389.5 720.6 397.1 728.1 397.1 737.3 397.1 746.6 389.5 754.1 380.3 754.1H296.5C287.3 754.1 279.7 746.6 279.7 737.3 279.7 728.1 287.3 720.6 296.5 720.6ZM296.5 787.6H464.1C473.3 787.6 480.8 795.1 480.8 804.4 480.8 813.6 473.3 821.1 464.1 821.1H296.5C287.3 821.1 279.7 813.6 279.7 804.4 279.7 795.1 287.3 787.6 296.5 787.6ZM256 187.5C259.6 190 262 193.9 262.8 198.3 263.5 202.7 262.5 207.2 259.9 210.8L176.1 328.1C173.2 332.1 168.7 334.7 163.8 335.1L162.4 335.1C158 335.1 153.7 333.4 150.6 330.2L117.1 296.7C110.7 290.2 110.8 279.7 117.3 273.2 123.7 266.8 134.2 266.7 140.8 273L160.3 292.6 232.6 191.4C235.2 187.7 239.1 185.3 243.5 184.6 247.9 183.8 252.3 184.9 256 187.5ZM162.4 234.6C162.4 243.9 154.9 251.4 145.7 251.4H95.4V351.9H196V335.1C196 325.9 203.5 318.4 212.7 318.4 222 318.4 229.5 325.9 229.5 335.1V351.9C229.5 370.4 214.5 385.4 196 385.4H95.4C76.9 385.4 61.9 370.4 61.9 351.9V251.4C61.9 232.9 76.9 217.8 95.4 217.8H145.7C154.9 217.8 162.4 225.3 162.4 234.6ZM162.4 234.6",
        "width": 1000
      },
      "search": [
        "checklist-1"
      ]
    },
    {
      "uid": "9a76bc135eac17d2c8b8ad4a5774fc87",
      "css": "download",
      "code": 59413,
      "src": "fontawesome"
    },
    {
      "uid": "qab5uvjyoc3uu4d2pvt8soshtgkuvpak",
      "css": "minus",
      "code": 59415,
      "src": "typicons"
    },
    {
      "uid": "5278ef7773e948d56c4d442c8c8c98cf",
      "css": "lightbulb",
      "code": 61675,
      "src": "fontawesome"
    },
    {
      "uid": "9dd9e835aebe1060ba7190ad2b2ed951",
      "css": "search",
      "code": 59416,
      "src": "fontawesome"
    },
    {
      "uid": "ec21fe3492bb04d9e29103c319556ed8",
      "css": "search-1",
      "code": 62733,
      "src": "mfglabs"
    },
    {
      "uid": "c6344a6ed148da12354cc90705287696",
      "css": "search-2",
      "code": 59417,
      "src": "iconic"
    },
    {
      "uid": "c709da589c923ba3c2ad48d9fc563e93",
      "css": "cancel-1",
      "code": 59419,
      "src": "entypo"
    },
    {
      "uid": "06301c50d89b5d3e651bd07ebd6d7de7",
      "css": "cancel-3",
      "code": 59421,
      "src": "mfglabs"
    },
    {
      "uid": "2d76f2c8d13be40694ecadfea7fb83c3",
      "css": "logout",
      "code": 59418,
      "src": "entypo"
    },
    {
      "uid": "a66e72da83c98248ae3ef43808efc452",
      "css": "plus-circle",
      "code": 59420,
      "src": "websymbols"
    },
    {
      "uid": "c311c48d79488965b0fab7f9cd12b6b5",
      "css": "left-open",
      "code": 59414,
      "src": "entypo"
    },
    {
      "uid": "b714be5a812a474811604f700dfc87ce",
      "css": "left-open-1",
      "code": 61447,
      "src": "mfglabs"
    },
    {
      "uid": "884cfc3e6e2d456dd2a2ca0dbb9e6337",
      "css": "left-open-big",
      "code": 59422,
      "src": "entypo"
    },
    {
      "uid": "059ee84db3ec1875f05b6b29e53c8cd1",
      "css": "chef",
      "code": 59392,
      "src": "custom_icons",
      "selected": false,
      "svg": {
        "path": "M996.7 364.4C996.7 236.5 892.8 132.5 765 132.5 759.4 132.5 753.8 132.8 748.2 133.2 693.2 50.5 600.1 0 500 0 400 0 306.8 50.5 251.8 133.2 246.2 132.8 240.6 132.5 235 132.5 107.2 132.5 3.3 236.5 3.3 364.4 3.3 481 89.8 577.7 202 593.8V914.2C202 961.5 240.5 1000 287.8 1000H712.2C759.5 1000 798 961.5 798 914.2V593.8C910.2 577.7 996.7 481 996.7 364.4ZM712.2 934H287.8C277.1 934 268 924.9 268 914.2V593.8C300.3 589.3 331 577.9 358.7 560.3 401.2 583.3 449.5 596.2 500 596.2S598.8 583.3 641.3 560.3C669 577.9 699.7 589.3 732 593.8V914.2C732 924.9 722.9 934 712.2 934ZM765 530.2C742.8 530.2 721.3 525.9 701.4 517.5 741.5 480.7 771.9 432.9 787.1 377.9 792 360.3 781.7 342.1 764.1 337.2 746.6 332.4 728.4 342.7 723.5 360.2 695.8 460.3 603.9 530.2 500 530.2S304.2 460.3 276.5 360.2C271.6 342.7 253.4 332.4 235.9 337.2 218.3 342.1 208 360.3 212.9 377.9 228.1 432.9 258.5 480.7 298.6 517.5 278.7 525.9 257.2 530.2 235 530.2 143.6 530.2 69.3 455.8 69.3 364.4 69.3 272.9 143.6 198.5 235 198.5 244.2 198.5 253.8 199.4 263.3 201 277 203.3 290.8 196.8 297.6 184.6 338.7 111.5 416.3 66 500 66S661.3 111.5 702.4 184.6C709.2 196.8 723 203.3 736.7 201 746.2 199.4 755.8 198.5 765 198.5 856.4 198.5 930.7 272.9 930.7 364.4 930.8 455.8 856.4 530.2 765 530.2Z",
        "width": 1000
      },
      "search": [
        "chef"
      ]
    },
    {
      "uid": "7dedf2969e8d5e6263b5f2b3ed8273d1",
      "css": "chef",
      "code": 59393,
      "src": "custom_icons",
      "selected": false,
      "svg": {
        "path": "M996.7 364.4C996.7 236.5 892.8 132.5 765 132.5 759.4 132.5 753.8 132.8 748.2 133.2 693.2 50.5 600.1 0 500 0 400 0 306.8 50.5 251.8 133.2 246.2 132.8 240.6 132.5 235 132.5 107.2 132.5 3.3 236.5 3.3 364.4 3.3 481 89.8 577.7 202 593.8V914.2C202 961.5 240.5 1000 287.8 1000H712.2C759.5 1000 798 961.5 798 914.2V593.8C910.2 577.7 996.7 481 996.7 364.4ZM712.2 934H287.8C277.1 934 268 924.9 268 914.2V593.8C300.3 589.3 331 577.9 358.7 560.3 401.2 583.3 449.5 596.2 500 596.2S598.8 583.3 641.3 560.3C669 577.9 699.7 589.3 732 593.8V914.2C732 924.9 722.9 934 712.2 934ZM765 530.2C742.8 530.2 721.3 525.9 701.4 517.5 741.5 480.7 771.9 432.9 787.1 377.9 792 360.3 781.7 342.1 764.1 337.2 746.6 332.4 728.4 342.7 723.5 360.2 695.8 460.3 603.9 530.2 500 530.2S304.2 460.3 276.5 360.2C271.6 342.7 253.4 332.4 235.9 337.2 218.3 342.1 208 360.3 212.9 377.9 228.1 432.9 258.5 480.7 298.6 517.5 278.7 525.9 257.2 530.2 235 530.2 143.6 530.2 69.3 455.8 69.3 364.4 69.3 272.9 143.6 198.5 235 198.5 244.2 198.5 253.8 199.4 263.3 201 277 203.3 290.8 196.8 297.6 184.6 338.7 111.5 416.3 66 500 66S661.3 111.5 702.4 184.6C709.2 196.8 723 203.3 736.7 201 746.2 199.4 755.8 198.5 765 198.5 856.4 198.5 930.7 272.9 930.7 364.4 930.8 455.8 856.4 530.2 765 530.2Z",
        "width": 1000
      },
      "search": [
        "chef"
      ]
    },
    {
      "uid": "de3f4a31af7517be9da9b604a27beb34",
      "css": "chef",
      "code": 59394,
      "src": "custom_icons",
      "selected": false,
      "svg": {
        "path": "M996.7 364.4C996.7 236.5 892.8 132.5 765 132.5 759.4 132.5 753.8 132.8 748.2 133.2 693.2 50.5 600.1 0 500 0 400 0 306.8 50.5 251.8 133.2 246.2 132.8 240.6 132.5 235 132.5 107.2 132.5 3.3 236.5 3.3 364.4 3.3 481 89.8 577.7 202 593.8V914.2C202 961.5 240.5 1000 287.8 1000H712.2C759.5 1000 798 961.5 798 914.2V593.8C910.2 577.7 996.7 481 996.7 364.4ZM712.2 934H287.8C277.1 934 268 924.9 268 914.2V593.8C300.3 589.3 331 577.9 358.7 560.3 401.2 583.3 449.5 596.2 500 596.2S598.8 583.3 641.3 560.3C669 577.9 699.7 589.3 732 593.8V914.2C732 924.9 722.9 934 712.2 934ZM765 530.2C742.8 530.2 721.3 525.9 701.4 517.5 741.5 480.7 771.9 432.9 787.1 377.9 792 360.3 781.7 342.1 764.1 337.2 746.6 332.4 728.4 342.7 723.5 360.2 695.8 460.3 603.9 530.2 500 530.2S304.2 460.3 276.5 360.2C271.6 342.7 253.4 332.4 235.9 337.2 218.3 342.1 208 360.3 212.9 377.9 228.1 432.9 258.5 480.7 298.6 517.5 278.7 525.9 257.2 530.2 235 530.2 143.6 530.2 69.3 455.8 69.3 364.4 69.3 272.9 143.6 198.5 235 198.5 244.2 198.5 253.8 199.4 263.3 201 277 203.3 290.8 196.8 297.6 184.6 338.7 111.5 416.3 66 500 66S661.3 111.5 702.4 184.6C709.2 196.8 723 203.3 736.7 201 746.2 199.4 755.8 198.5 765 198.5 856.4 198.5 930.7 272.9 930.7 364.4 930.8 455.8 856.4 530.2 765 530.2Z",
        "width": 1000
      },
      "search": [
        "chef"
      ]
    },
    {
      "uid": "4af797912b1b7b86d6595689468afff3",
      "css": "chef",
      "code": 59395,
      "src": "custom_icons",
      "selected": false,
      "svg": {
        "path": "M996.7 364.4C996.7 236.5 892.8 132.5 765 132.5 759.4 132.5 753.8 132.8 748.2 133.2 693.2 50.5 600.1 0 500 0 400 0 306.8 50.5 251.8 133.2 246.2 132.8 240.6 132.5 235 132.5 107.2 132.5 3.3 236.5 3.3 364.4 3.3 481 89.8 577.7 202 593.8V914.2C202 961.5 240.5 1000 287.8 1000H712.2C759.5 1000 798 961.5 798 914.2V593.8C910.2 577.7 996.7 481 996.7 364.4ZM712.2 934H287.8C277.1 934 268 924.9 268 914.2V593.8C300.3 589.3 331 577.9 358.7 560.3 401.2 583.3 449.5 596.2 500 596.2S598.8 583.3 641.3 560.3C669 577.9 699.7 589.3 732 593.8V914.2C732 924.9 722.9 934 712.2 934ZM765 530.2C742.8 530.2 721.3 525.9 701.4 517.5 741.5 480.7 771.9 432.9 787.1 377.9 792 360.3 781.7 342.1 764.1 337.2 746.6 332.4 728.4 342.7 723.5 360.2 695.8 460.3 603.9 530.2 500 530.2S304.2 460.3 276.5 360.2C271.6 342.7 253.4 332.4 235.9 337.2 218.3 342.1 208 360.3 212.9 377.9 228.1 432.9 258.5 480.7 298.6 517.5 278.7 525.9 257.2 530.2 235 530.2 143.6 530.2 69.3 455.8 69.3 364.4 69.3 272.9 143.6 198.5 235 198.5 244.2 198.5 253.8 199.4 263.3 201 277 203.3 290.8 196.8 297.6 184.6 338.7 111.5 416.3 66 500 66S661.3 111.5 702.4 184.6C709.2 196.8 723 203.3 736.7 201 746.2 199.4 755.8 198.5 765 198.5 856.4 198.5 930.7 272.9 930.7 364.4 930.8 455.8 856.4 530.2 765 530.2Z",
        "width": 1000
      },
      "search": [
        "chef"
      ]
    },
    {
      "uid": "77eaa61b7240fec4692dc4290d85b691",
      "css": "chef-cooker-hat",
      "code": 59396,
      "src": "custom_icons",
      "selected": false,
      "svg": {
        "path": "M773.4 924.4V975.8C773.4 989.2 762.6 1000 749.2 1000H250.8C237.4 1000 226.6 989.2 226.6 975.8V924.4H773.4ZM749.2 130.9C738.1 130.9 726.9 131.6 715.8 133.2 675.1 51.7 592.4 0 500 0S324.9 51.7 284.2 133.2C273.1 131.6 261.9 130.9 250.8 130.9 117.6 130.9 9.4 239.2 9.4 372.3 9.4 497.2 104.8 600.3 226.6 612.5V876H296.1V626.9C296.1 613.5 307 602.7 320.3 602.7S344.5 613.5 344.5 626.9V876H475.8V626.9C475.8 613.5 486.6 602.7 500 602.7S524.2 613.5 524.2 626.9V876H655.5V626.9C655.5 613.5 666.3 602.7 679.7 602.7S703.9 613.5 703.9 626.9V876H773.4V612.5C895.2 600.3 990.7 497.2 990.7 372.3 990.7 239.2 882.4 130.9 749.2 130.9Z",
        "width": 1000
      },
      "search": [
        "chef-cooker-hat"
      ]
    }
  ]
}